backwardpipl/__init__.py
backwardpipl/backwardpipl.py
backwardpipl-0.2.1.dist-info/licenses/LICENSE
backwardpipl-0.2.1.dist-info/METADATA
backwardpipl-0.2.1.dist-info/WHEEL
backwardpipl-0.2.1.dist-info/top_level.txt
backwardpipl-0.2.1.dist-info/RECORD
