Metadata-Version: 2.4
Name: backwardpipl
Version: 0.2.1
Summary: A function decoration that let the function go backward by setting the new argument backward to True.
Author-email: Cedrick Gauthier <spinachlang@proton.me>
License: MIT
Requires-Python: >=3.10
License-File: LICENSE
Requires-Dist: dill==0.4.0
Dynamic: license-file
